content_safety_text/__init__.py
content_safety_text/tools/__init__.py
content_safety_text/tools/content_safety_text_tool.py
content_safety_text/tools/utils.py
content_safety_text/yamls/content_safety_text_tool.yaml
tests/__init__.py
tests/test_content_safety_text_tool.py
content_safety_text-0.0.4.dist-info/METADATA
content_safety_text-0.0.4.dist-info/WHEEL
content_safety_text-0.0.4.dist-info/entry_points.txt
content_safety_text-0.0.4.dist-info/top_level.txt
content_safety_text-0.0.4.dist-info/RECORD
