Metadata-Version: 2.1
Name: content-safety-text
Version: 0.0.4
Summary: This is my tools package
